pydeezloader/__init__.py
pydeezloader/deezer_settings.py
pydeezloader/deezweb_utils.py
pydeezloader/download_utils.py
pydeezloader/exceptions.py
pydeezloader/methods.py
pydeezloader/others_settings.py
pydeezloader/utils.py
pydeezloader/bin/deez-dw.py
pydeezloader/bin/deez-web.py
pydeezloader-1.2.data/scripts/deez-dw.py
pydeezloader-1.2.data/scripts/deez-web.py
pydeezloader-1.2.dist-info/LICENSE
pydeezloader-1.2.dist-info/METADATA
pydeezloader-1.2.dist-info/WHEEL
pydeezloader-1.2.dist-info/top_level.txt
pydeezloader-1.2.dist-info/RECORD
