Metadata-Version: 2.1
Name: pydeezloader
Version: 1.2
Summary: Download Songs, Albums and Playlists - from Deezer and Spotify.
Home-page: https://github.com/TheDeezLoader/pyDeezloader
Author: BlackStoneReborn
Author-email: BlackStoneOfficial3@gmail.com
License: GNU General Public License V3+
Platform: UNKNOWN
Classifier: License :: OSI Approved :: GNU General Public License v3 (GPLv3)
Classifier: Programming Language :: Python :: 3
Classifier: Programming Language :: Python :: 3 :: Only
Classifier: Programming Language :: Python :: 3.6
Classifier: Programming Language :: Python :: 3.7
Classifier: Programming Language :: Python :: 3.8
Classifier: Programming Language :: Python :: 3.9
Classifier: Programming Language :: Python :: Implementation :: CPython
Classifier: Programming Language :: Python :: Implementation :: PyPy
Requires-Python: >=3.6.1
Requires-Dist: Flask
Requires-Dist: flask-cors
Requires-Dist: stagger
Requires-Dist: mutagen
Requires-Dist: pycryptodome
Requires-Dist: requests (>=2.25.0)
Requires-Dist: spotipy
Requires-Dist: tqdm
Requires-Dist: six (>=1.15.0)
